Metadata-Version: 2.1
Name: cai-causal-effects
Version: 0.0.0
Summary: Causal effect estimation.
Author: causaLens
Author-email: opensource@causalens.com
Requires-Python: >=3.8,<4.0
Classifier: Programming Language :: Python :: 3
Classifier: Programming Language :: Python :: 3.8
Classifier: Programming Language :: Python :: 3.9
Classifier: Programming Language :: Python :: 3.10
Classifier: Programming Language :: Python :: 3.11
